semanticlens/__init__.py
semanticlens/lens.py
semanticlens/scores.py
semanticlens/component_visualization/__init__.py
semanticlens/component_visualization/activation_based.py
semanticlens/component_visualization/activation_caching.py
semanticlens/component_visualization/aggregators.py
semanticlens/component_visualization/base.py
semanticlens/component_visualization/relevance_based.py
semanticlens/foundation_models/__init__.py
semanticlens/foundation_models/base.py
semanticlens/foundation_models/clip.py
semanticlens/utils/__init__.py
semanticlens/utils/helper.py
semanticlens/utils/log_setup.py
semanticlens/utils/render.py
semanticlens-0.2.1.dist-info/METADATA
semanticlens-0.2.1.dist-info/WHEEL
semanticlens-0.2.1.dist-info/licenses/LICENSE
semanticlens-0.2.1.dist-info/RECORD
