Metadata-Version: 2.4
Name: semanticlens
Version: 0.2.1
Summary: A package for mechanistic understanding and validation of large  AI model with SemanticLens
Author-email: Jim Berend <jim.berend@hhi.fraunhofer.de>, Maximilian Dreyer <maximilian.dreyer@hhi.fraunhofer.de>
License-Expression: BSD-3-Clause
License-File: LICENSE
Keywords: deep learning,foundation model,mechanistic interpretability,semantic analysis
Requires-Python: >=3.9
Requires-Dist: einops>=0.8.1
Requires-Dist: open-clip-torch>=3.0.0
Requires-Dist: scikit-learn>=1.6.1
Requires-Dist: timm>=1.0.19
Requires-Dist: torch>=2.7.1
Requires-Dist: transformers>=4.54.1
Requires-Dist: zennit-crp>=0.6.0
